[{"__symbolic":"module","version":3,"metadata":{},"exports":[{"from":"./src/user-admin.module","export":["UserAdminModule"]},{"from":"./src/users.service","export":["UsersService"]},{"from":"./src/user-list.component","export":["UserListComponent"]}]},{"__symbolic":"module","version":1,"metadata":{},"exports":[{"from":"./src/user-admin.module","export":["UserAdminModule"]},{"from":"./src/users.service","export":["UsersService"]},{"from":"./src/user-list.component","export":["UserListComponent"]}]}]